Inflow/__init__.py
Inflow/automatic_tests/__init__.py
Inflow/bins/__init__.py
Inflow/bins/content.py
Inflow/bins/piezzo_stimulations.py
Inflow/core/__init__.py
Inflow/core/config.py
Inflow/core/decorators.py
Inflow/core/logging.py
Inflow/core/optimization.py
Inflow/core/pipelining.py
Inflow/core/special_types.py
Inflow/core/time.py
Inflow/core/utils.py
Inflow/ios/__init__.py
Inflow/ios/helpers.py
Inflow/ios/load.py
Inflow/ios/matlab.py
Inflow/ios/save.py
Inflow/masks/__init__.py
Inflow/masks/create.py
Inflow/notebook_templating/__init__.py
Inflow/pandex/__init__.py
Inflow/pandex/accessors.py
Inflow/path/__init__.py
Inflow/path/extract.py
Inflow/path/find.py
Inflow/path/one_alf.py
Inflow/path/pattern.py
Inflow/plots/__init__.py
Inflow/plots/artists.py
Inflow/plots/captions.py
Inflow/plots/colors.py
Inflow/plots/custom.py
Inflow/plots/graphviz.py
Inflow/plots/utils.py
Inflow/signal/__init__.py
Inflow/signal/filters.py
Inflow/signal/fits.py
Inflow/signal/fluo.py
Inflow/signal/norms.py
Inflow/signal/resample.py
Inflow/tdms/__init__.py
Inflow/tdms/content.py
Inflow/tiff/__init__.py
Inflow/tiff/content.py
Inflow/tiff/tiff_metadata_parse.dll
inflow_haisslab-1.2.42.dist-info/METADATA
inflow_haisslab-1.2.42.dist-info/WHEEL
inflow_haisslab-1.2.42.dist-info/entry_points.txt
inflow_haisslab-1.2.42.dist-info/licenses/LICENSE
inflow_haisslab-1.2.42.dist-info/RECORD
