Metadata-Version: 2.4
Name: inflow-haisslab
Version: 1.2.42
Summary: General python code for analysis pipeline
Project-URL: Homepage, https://gitlab.pasteur.fr/haisslab/analysis-packages/Inflow
Author-email: Timothé JOST-MOUSSEAU <timothe.jost-mousseau@pasteur.com>
License: MIT
License-File: LICENSE
Classifier: Development Status :: 3 - Alpha
Classifier: Intended Audience :: Developers
Classifier: License :: OSI Approved :: MIT License
Classifier: Programming Language :: Python :: 3.11
Requires-Python: <3.14,>=3.11
Requires-Dist: concurrent-log-handler>=0.9
Requires-Dist: h5py>=3.7
Requires-Dist: matplotlib>=3.6
Requires-Dist: natsort>=8.2
Requires-Dist: nptdms>=1.6
Requires-Dist: numpy>=1.23
Requires-Dist: opencv-python-headless>=4.6
Requires-Dist: pandas>=1.4
Requires-Dist: paramiko>=2.8
Requires-Dist: scanimage-tiff-reader>=1.4.1
Requires-Dist: scipy>=1.9
Requires-Dist: seaborn>=0.11
Requires-Dist: shapely>=2.0.6
Requires-Dist: timelined-array>=0.0.14
Provides-Extra: gui
Requires-Dist: suite2p-haisslab[gui]>=0.14.11; extra == 'gui'
Provides-Extra: lab-env
Requires-Dist: alyx-connector<2,>=1.3.2; extra == 'lab-env'
Provides-Extra: test
Requires-Dist: pytest-cov>=5.0.0; extra == 'test'
Requires-Dist: pytest>=8.3.2; extra == 'test'
